subrun/__init__.py
subrun/__main__.py
subrun/dto/__init__.py
subrun/error/__init__.py
subrun/pipeline/__init__.py
subrun/pyrustic_data/backstage/data/build_report.json
subrun/pyrustic_data/backstage/hooking/build.json
subrun/pyrustic_data/backstage/hooking/init.json
subrun/pyrustic_data/backstage/hooking/release.json
tests/__init__.py
tests/__main__.py
subrun-0.0.7.dist-info/LICENSE
subrun-0.0.7.dist-info/METADATA
subrun-0.0.7.dist-info/WHEEL
subrun-0.0.7.dist-info/entry_points.txt
subrun-0.0.7.dist-info/top_level.txt
subrun-0.0.7.dist-info/RECORD
