Metadata-Version: 2.1
Name: subrun
Version: 0.0.7
Summary: Intuitive API to safely start and communicate with processes in Python
Home-page: https://github.com/pyrustic/subrun
Author: Pyrustic Evangelist
Author-email: rusticalex@yahoo.com
Maintainer: Pyrustic Evangelist
Maintainer-email: rusticalex@yahoo.com
License: MIT
Keywords: library,subprocess,spawner,stdin,stdout,stderr,communicate,interact,process,spawn,commands,pipeline,pyrustic
Platform: UNKNOWN
Classifier: Programming Language :: Python :: 3
Classifier: License :: OSI Approved :: MIT License
Classifier: Operating System :: OS Independent
Requires-Python: >=3.5
License-File: LICENSE
